DeepTalk_ST/__init__.py
DeepTalk_ST/cci_vis.py
DeepTalk_ST/decon_utils.py
DeepTalk_ST/map_utils.py
DeepTalk_ST/plot_utils.py
DeepTalk_ST/utils.py
DeepTalk_ST/models/__init__.py
DeepTalk_ST/models/decon.py
DeepTalk_ST/models/match.py
DeepTalk_ST/src/__init__.py
DeepTalk_ST/src/finetuning.py
DeepTalk_ST/src/pretraining.py
DeepTalk_ST/src/CompGCN/__init__.py
DeepTalk_ST/src/CompGCN/data_loader.py
DeepTalk_ST/src/CompGCN/helper.py
DeepTalk_ST/src/CompGCN/run.py
DeepTalk_ST/src/CompGCN/model/__init__.py
DeepTalk_ST/src/CompGCN/model/compgcn_conv.py
DeepTalk_ST/src/CompGCN/model/compgcn_conv_basis.py
DeepTalk_ST/src/CompGCN/model/message_passing.py
DeepTalk_ST/src/CompGCN/model/models.py
DeepTalk_ST/src/ccc_model/__init__.py
DeepTalk_ST/src/ccc_model/ccc_model.py
DeepTalk_ST/src/ccc_model/mask_generation.py
DeepTalk_ST/src/ccc_model/process_walks_gcn.py
DeepTalk_ST/src/encoding/__init__.py
DeepTalk_ST/src/encoding/gcn_graph_encoder.py
DeepTalk_ST/src/encoding/gcn_transform.py
DeepTalk_ST/src/encoding/input_encoder.py
DeepTalk_ST/src/processing/__init__.py
DeepTalk_ST/src/processing/attributed_graph.py
DeepTalk_ST/src/processing/coherent_context_generator.py
DeepTalk_ST/src/processing/context_generator.py
DeepTalk_ST/src/processing/generic_attributed_graph.py
DeepTalk_ST/src/processing/negative_sampling.py
DeepTalk_ST/src/processing/process_unb_cyber_network.py
DeepTalk_ST/src/processing/test/__init__.py
DeepTalk_ST/src/processing/test/test_negative_sampling.py
DeepTalk_ST/src/utils/__init__.py
DeepTalk_ST/src/utils/context_metrics.py
DeepTalk_ST/src/utils/data_utils.py
DeepTalk_ST/src/utils/evaluation.py
DeepTalk_ST/src/utils/link_predict.py
DeepTalk_ST/src/utils/transform_to_1_based.py
DeepTalk_ST/src/utils/utils.py
DeepTalk_ST-0.0.12.dist-info/LICENSE.md
DeepTalk_ST-0.0.12.dist-info/METADATA
DeepTalk_ST-0.0.12.dist-info/WHEEL
DeepTalk_ST-0.0.12.dist-info/top_level.txt
DeepTalk_ST-0.0.12.dist-info/RECORD
