Metadata-Version: 2.1
Name: DeepTalk-ST
Version: 0.0.12
Summary: Cell-cell communication prediction for ST data 
Home-page: https://github.com/xiaoshaziydy/DeepTalktest
Author: WenyiYang
Author-email: wenyiyang22@163.com
License: MIT License
Keywords: cell-cell communicaiton,spatial transcriptomics,deep learning
Classifier: Programming Language :: Python :: 3.8
Classifier: License :: OSI Approved :: MIT License
Classifier: Operating System :: OS Independent
Requires-Python: >=3.6
License-File: LICENSE.md
Requires-Dist: scanpy >=1.9.6
Requires-Dist: anndata >=0.9.2
Requires-Dist: numpy >=1.22.4
Requires-Dist: scipy >=1.10.1
Requires-Dist: pandas >=2.0.3
Requires-Dist: scikit-learn >=1.3.2
Requires-Dist: statsmodels >=0.14.0
Requires-Dist: igraph >=0.10.8
Requires-Dist: pynndescent >=0.5.10
Requires-Dist: squidpy >=1.2.3
